{
  "ApiConfig": {
    "AuthURL": "https://uatapiclaroid.claropay.com/claroid/claroID/oauth2/token",
    "ClaropayURL": "https://appsuat.claropay.com:11616/uat-tpayment/tpayment/v1/payment/",
    "apiUsername": "FARMACIASGUADALAJARA",
    "apiPassword": "jd5Xal3Cx2mb7o"
  },
  "AllowedHosts": "*",
  "ConnectionStrings": {
    "DefaultConnection": "server=10.100.11.60;user=user_operator;password=Y4Ps1Us3r_RMTE;port=3306;database=claropay"
    //"DefaultConnection": "server=localhost;user=root;password=fragua;database=claropay;port=22033"
  },
  "Logging": {
    "LogLevel": {
      "Default": "Information",
      "Microsoft.AspNetCore": "Warning"
    }
  }

}
